boxpython/__init__.py
boxpython/auth.py
boxpython/exceptions.py
boxpython/request.py
boxpython/session.py
boxpython/upload.py
boxpython-1.0.5.dist-info/DESCRIPTION.rst
boxpython-1.0.5.dist-info/METADATA
boxpython-1.0.5.dist-info/metadata.json
boxpython-1.0.5.dist-info/RECORD
boxpython-1.0.5.dist-info/top_level.txt
boxpython-1.0.5.dist-info/WHEEL
